CTApy/__init__.py
CTApy/allocate_topics.py
CTApy/calculate_clusters.py
CTApy/calculate_quality_all.py
CTApy/create_cosine_matrix.py
CTApy/optimize_clusters.py
CTApy/prediction.py
CTApy/preprocessing.py
CTApy/tag_text.py
CTApy/word_importance.py
CTApy-0.1.4.dist-info/METADATA
CTApy-0.1.4.dist-info/WHEEL
CTApy-0.1.4.dist-info/license.txt
CTApy-0.1.4.dist-info/top_level.txt
CTApy-0.1.4.dist-info/RECORD
