Metadata-Version: 2.1
Name: CTApy
Version: 0.1.4
Summary: Python package for the Conditional Topic Allocation (CTA)
Home-page: https://github.com/twekhof/CTA
Author: Tobias Wekhof
Author-email: tobiaswekhof@gmail.com
License: MIT
Classifier: Programming Language :: Python :: 3
Classifier: License :: OSI Approved :: MIT License
Classifier: Operating System :: OS Independent
Requires-Python: >=3.9
License-File: license.txt
Requires-Dist: gensim >=4.3.2
Requires-Dist: nltk >=3.8.1
Requires-Dist: numpy >=1.24.3
Requires-Dist: pandas >=2.0.3
Requires-Dist: scipy >=1.11.1
Requires-Dist: shap >=0.44.0
Requires-Dist: spacy >=3.7.2
Requires-Dist: torch >=1.2.1
Requires-Dist: tqdm >=4.65.0
Requires-Dist: transformers >=4.32.1
